pipfilter/__init__.py
pipfilter/pipfilter.py
pipfilter-0.1.1.dist-info/entry_points.txt
pipfilter-0.1.1.dist-info/LICENSE
pipfilter-0.1.1.dist-info/METADATA
pipfilter-0.1.1.dist-info/WHEEL
pipfilter-0.1.1.dist-info/RECORD
